{"errors":[],"warnings":[],"namedChunkGroups":{"polyfill":{"chunks":[0,3],"assets":["webpack-runtime-71e046241d7d5cdf707d.js","webpack-runtime-71e046241d7d5cdf707d.js.map","polyfill-68ba508330bedc2aeb6a.js","polyfill-68ba508330bedc2aeb6a.js.map"],"children":{},"childAssets":{}},"app":{"chunks":[0,2,1],"assets":["webpack-runtime-71e046241d7d5cdf707d.js","webpack-runtime-71e046241d7d5cdf707d.js.map","framework-04017db0dec66097c42d.js","framework-04017db0dec66097c42d.js.map","app-0b0b85fb8c99db54cdaf.js","app-0b0b85fb8c99db54cdaf.js.map"],"children":{},"childAssets":{}}},"assetsByChunkName":{"polyfill":["webpack-runtime-71e046241d7d5cdf707d.js","polyfill-68ba508330bedc2aeb6a.js"],"app":["webpack-runtime-71e046241d7d5cdf707d.js","framework-04017db0dec66097c42d.js","app-0b0b85fb8c99db54cdaf.js"]}}